expositor/__init__.py
expositor/__main__.py
expositor/client.py
expositor/exception.py
expositor/helpers.py
expositor/stream.py
expositor/threatnet.py
expositor/cli/__init__.py
expositor/cli/alert.py
expositor/cli/data.py
expositor/cli/helpers.py
expositor/cli/host.py
expositor/cli/organization.py
expositor/cli/scan.py
expositor/cli/settings.py
expositor/cli/worldmap.py
expositor/cli/converter/__init__.py
expositor/cli/converter/base.py
expositor/cli/converter/csvc.py
expositor/cli/converter/excel.py
expositor/cli/converter/geojson.py
expositor/cli/converter/images.py
expositor/cli/converter/kml.py
expositor-2021.6.dev1.dist-info/LICENSE
expositor-2021.6.dev1.dist-info/WHEEL
expositor-2021.6.dev1.dist-info/METADATA
expositor-2021.6.dev1.dist-info/RECORD
